git_auto/__init__.py
git_auto/prompt_presets/commit_prompt.txt
git_auto/prompt_presets/validation_prompt.txt
git_auto/src/__init__.py
git_auto/src/ai_interface.py
git_auto/src/cli.py
git_auto/src/config.py
git_auto/src/git_utils.py
git_auto/src/sanitizer.py
git_auto/src/validation.py
git_auto/templates/minimal_output.txt
git_auto/templates/standard_output.txt
git_auto-0.1.3.dist-info/METADATA
git_auto-0.1.3.dist-info/WHEEL
git_auto-0.1.3.dist-info/entry_points.txt
git_auto-0.1.3.dist-info/top_level.txt
git_auto-0.1.3.dist-info/RECORD
