Metadata-Version: 2.4
Name: git-auto
Version: 0.1.3
Summary: AI-powered Git commit helper using Google Gemini
Author-email: Valentin Petrov <valentin.petrov@gitopsnow.com>
License: MIT
Project-URL: Homepage, https://github.com/oxie/git-auto
Project-URL: Bug Tracker, https://github.com/oxie/git-auto/issues
Keywords: git,commit,ai,gemini,developer tools,cli,automation
Classifier: Programming Language :: Python :: 3
Classifier: License :: OSI Approved :: MIT License
Classifier: Operating System :: OS Independent
Classifier: Development Status :: 3 - Alpha
Classifier: Environment :: Console
Classifier: Intended Audience :: Developers
Classifier: Topic :: Software Development :: Version Control :: Git
Classifier: Topic :: Text Processing :: Linguistic
Requires-Python: >=3.8
Requires-Dist: click>=8.0
Requires-Dist: google-generativeai>=0.4
Requires-Dist: python-dotenv>=0.20
Requires-Dist: PyYAML>=6.0
Requires-Dist: pydantic>=2.0
Requires-Dist: Jinja2>=3.0
Requires-Dist: rich>=13.0
Requires-Dist: toml>=0.10
Provides-Extra: linter
Requires-Dist: yamllint>=1.26; extra == "linter"
Provides-Extra: dev
Requires-Dist: pytest>=7.0; extra == "dev"
Requires-Dist: pytest-mock; extra == "dev"
Requires-Dist: ruff>=0.1; extra == "dev"
Requires-Dist: mypy>=1.0; extra == "dev"
